[
  {
    "nickname": "장군이",
    "reviews": 15,
    "profileImg": "https://cdn.pixabay.com/photo/2022/07/06/13/10/vintage-car-7305109_1280.jpg",
    "rate": 10,
    "reviewText": "금방 연남동 더다이닝랩 맛있다 후기를 남겼는데, 그 이상으로 맛있게 먹었던 파델라! 전체적인 분위기나 음식들이 더다이닝랩에 비하면 좀 더 캐주얼한 느낌이라 다른 분께서 외할머니가 해주신 이태리 가정식이라고 표현하신 말이 참 와닿았던 것 같아요.에피타이저로 나오는 부르스게타, 먹물리조또, 가지피자, 빼쉐파스타 모두 맛이 너무 과하거나 부족한 것 없이 맛있었습니다. 특히 이탈리안피자, 가지를 좋아한다면 좋아하지 않을수 없음 ㅋㅋ 가지피자 비주얼에 반해서 오게 된 곳인데, 역시 맛있네요!양이 생각보다 많아서 좀 남겼는데 너무 아쉬워요 흑흑 재방문 의사 있습니다!!!여기도 4인이 최대이지만 예약 가능하고, 맛도 좋아서 만약 연남동에서 딱히 정한곳 없이 이탈리안을 먹고 싶으면 잫을 곳 같아요! 갠적으로 더 다이닝랩보다 여기가 더 좋았어용 ㅎㅎ 더다이닝랩은 소개팅장소로 좋을 듯",
    "reviewDate": "2022-8-1",
    "reviewImg": [
      "https://cdn.pixabay.com/photo/2022/07/06/13/10/vintage-car-7305109_1280.jpg",
      "https://cdn.pixabay.com/photo/2022/07/06/13/10/vintage-car-7305109_1280.jpg",
      "https://cdn.pixabay.com/photo/2022/07/06/13/10/vintage-car-7305109_1280.jpg",
      "https://cdn.pixabay.com/photo/2022/07/06/13/10/vintage-car-7305109_1280.jpg"
    ],
    "reviewCount": 3
  },
  {
    "nickname": "우뇨니",
    "reviews": 15,
    "profileImg": "https://cdn.pixabay.com/photo/2022/07/06/13/10/vintage-car-7305109_1280.jpg",
    "rate": 6,
    "reviewText": "금방 연남동 더다이닝랩 맛있다 후기를 남겼는데, 그 이상으로 맛있게 먹었던 파델라! 전체적인 분위기나 음식들이 더다이닝랩에 비하면 좀 더 캐주얼한 느낌이라 다른 분께서 외할머니가 해주신 이태리 가정식이라고 표현하신 말이 참 와닿았던 것 같아요.에피타이저로 나오는 부르스게타, 먹물리조또, 가지피자, 빼쉐파스타 모두 맛이 너무 과하거나 부족한 것 없이 맛있었습니다. 특히 이탈리안피자, 가지를 좋아한다면 좋아하지 않을수 없음 ㅋㅋ 가지피자 비주얼에 반해서 오게 된 곳인데, 역시 맛있네요!양이 생각보다 많아서 좀 남겼는데 너무 아쉬워요 흑흑 재방문 의사 있습니다!!!여기도 4인이 최대이지만 예약 가능하고, 맛도 좋아서 만약 연남동에서 딱히 정한곳 없이 이탈리안을 먹고 싶으면 잫을 곳 같아요! 갠적으로 더 다이닝랩보다 여기가 더 좋았어용 ㅎㅎ 더다이닝랩은 소개팅장소로 좋을 듯",
    "reviewDate": "2022-6-8",

    "reviewImg": [
      "https://cdn.pixabay.com/photo/2022/07/06/13/10/vintage-car-7305109_1280.jpg",
      "https://cdn.pixabay.com/photo/2022/07/06/13/10/vintage-car-7305109_1280.jpg",
      "https://cdn.pixabay.com/photo/2022/07/06/13/10/vintage-car-7305109_1280.jpg",
      "https://cdn.pixabay.com/photo/2022/07/06/13/10/vintage-car-7305109_1280.jpg"
    ],
    "reviewCount": 3
  },
  {
    "nickname": "아롱이",
    "reviews": 13,
    "profileImg": "https://cdn.pixabay.com/photo/2022/07/06/13/10/vintage-car-7305109_1280.jpg",
    "rate": 1,
    "reviewText": "금방 연남동 더다이닝랩 맛있다 후기를 남겼는데, 그 이상으로 맛있게 먹었던 파델라! 전체적인 분위기나 음식들이 더다이닝랩에 비하면 좀 더 캐주얼한 느낌이라 다른 분께서 외할머니가 해주신 이태리 가정식이라고 표현하신 말이 참 와닿았던 것 같아요.에피타이저로 나오는 부르스게타, 먹물리조또, 가지피자, 빼쉐파스타 모두 맛이 너무 과하거나 부족한 것 없이 맛있었습니다. 특히 이탈리안피자, 가지를 좋아한다면 좋아하지 않을수 없음 ㅋㅋ 가지피자 비주얼에 반해서 오게 된 곳인데, 역시 맛있네요!양이 생각보다 많아서 좀 남겼는데 너무 아쉬워요 흑흑 재방문 의사 있습니다!!!여기도 4인이 최대이지만 예약 가능하고, 맛도 좋아서 만약 연남동에서 딱히 정한곳 없이 이탈리안을 먹고 싶으면 잫을 곳 같아요! 갠적으로 더 다이닝랩보다 여기가 더 좋았어용 ㅎㅎ 더다이닝랩은 소개팅장소로 좋을 듯",
    "reviewDate": "2022-7-31",
    "reviewImg": [
      "https://cdn.pixabay.com/photo/2022/07/06/13/10/vintage-car-7305109_1280.jpg",
      "https://cdn.pixabay.com/photo/2022/07/06/13/10/vintage-car-7305109_1280.jpg",
      "https://cdn.pixabay.com/photo/2022/07/06/13/10/vintage-car-7305109_1280.jpg",
      "https://cdn.pixabay.com/photo/2022/07/06/13/10/vintage-car-7305109_1280.jpg"
    ],
    "reviewCount": 3
  },
  {
    "nickname": "장군이",
    "reviews": 15,
    "profileImg": "https://cdn.pixabay.com/photo/2022/07/06/13/10/vintage-car-7305109_1280.jpg",
    "rate": 10,
    "reviewText": "금방 연남동 더다이닝랩 맛있다 후기를 남겼는데, 그 이상으로 맛있게 먹었던 파델라! 전체적인 분위기나 음식들이 더다이닝랩에 비하면 좀 더 캐주얼한 느낌이라 다른 분께서 외할머니가 해주신 이태리 가정식이라고 표현하신 말이 참 와닿았던 것 같아요.에피타이저로 나오는 부르스게타, 먹물리조또, 가지피자, 빼쉐파스타 모두 맛이 너무 과하거나 부족한 것 없이 맛있었습니다. 특히 이탈리안피자, 가지를 좋아한다면 좋아하지 않을수 없음 ㅋㅋ 가지피자 비주얼에 반해서 오게 된 곳인데, 역시 맛있네요!양이 생각보다 많아서 좀 남겼는데 너무 아쉬워요 흑흑 재방문 의사 있습니다!!!여기도 4인이 최대이지만 예약 가능하고, 맛도 좋아서 만약 연남동에서 딱히 정한곳 없이 이탈리안을 먹고 싶으면 잫을 곳 같아요! 갠적으로 더 다이닝랩보다 여기가 더 좋았어용 ㅎㅎ 더다이닝랩은 소개팅장소로 좋을 듯",
    "reviewDate": "2022-8-1",
    "reviewImg": [
      "https://cdn.pixabay.com/photo/2022/07/06/13/10/vintage-car-7305109_1280.jpg",
      "https://cdn.pixabay.com/photo/2022/07/06/13/10/vintage-car-7305109_1280.jpg",
      "https://cdn.pixabay.com/photo/2022/07/06/13/10/vintage-car-7305109_1280.jpg",
      "https://cdn.pixabay.com/photo/2022/07/06/13/10/vintage-car-7305109_1280.jpg"
    ],
    "reviewCount": 3
  }
]
